odoo9_addon_business_requirement_deliverable_categ-9.0.1.0.0.99.dev7-py2.7-nspkg.pth
odoo_addons/business_requirement_deliverable_categ/__openerp__.py
odoo_addons/business_requirement_deliverable_categ/__init__.py
odoo_addons/business_requirement_deliverable_categ/README.rst
odoo_addons/business_requirement_deliverable_categ/models/business_requirement_resource.py
odoo_addons/business_requirement_deliverable_categ/models/__init__.py
odoo_addons/business_requirement_deliverable_categ/views/business_requirement_resource.xml
odoo_addons/business_requirement_deliverable_categ/static/img/bus_req_tags.png
odoo_addons/business_requirement_deliverable_categ/static/description/icon.png
odoo9_addon_business_requirement_deliverable_categ-9.0.1.0.0.99.dev7.dist-info/top_level.txt
odoo9_addon_business_requirement_deliverable_categ-9.0.1.0.0.99.dev7.dist-info/WHEEL
odoo9_addon_business_requirement_deliverable_categ-9.0.1.0.0.99.dev7.dist-info/RECORD
odoo9_addon_business_requirement_deliverable_categ-9.0.1.0.0.99.dev7.dist-info/metadata.json
odoo9_addon_business_requirement_deliverable_categ-9.0.1.0.0.99.dev7.dist-info/DESCRIPTION.rst
odoo9_addon_business_requirement_deliverable_categ-9.0.1.0.0.99.dev7.dist-info/METADATA
odoo9_addon_business_requirement_deliverable_categ-9.0.1.0.0.99.dev7.dist-info/namespace_packages.txt
